uni-0.0.dist-info/RECORD
uni-0.0.dist-info/METADATA
uni-0.0.dist-info/metadata.json
uni-0.0.dist-info/WHEEL
uni-0.0.dist-info/DESCRIPTION.rst
uni-0.0.dist-info/top_level.txt
uni/assertions.py
uni/checker.py
uni/__init__.py
