Metadata-Version: 2.0
Name: uni
Version: 0.0
Summary: Execute mongo-style queries on dictionaries.
Home-page: http://github.com/twneale/uni
Author: Thom Neale
Author-email: twneale@gmail.com
License: UNKNOWN
Platform: any
Classifier: Development Status :: 4 - Beta
Classifier: Intended Audience :: Developers
Classifier: License :: OSI Approved :: BSD License
Classifier: Natural Language :: English
Classifier: Operating System :: OS Independent
Classifier: Programming Language :: Python :: 3.4
Requires-Dist: nmmd
